README.md
setup.py
cwutils/__init__.py
cwutils/memory.py
cwutils/nums.py
cwutils/time.py
cwutils.egg-info/PKG-INFO
cwutils.egg-info/SOURCES.txt
cwutils.egg-info/dependency_links.txt
cwutils.egg-info/requires.txt
cwutils.egg-info/top_level.txt