Metadata-Version: 2.1
Name: cwutils
Version: 1.1.1a0
Summary: Utils by Chaos and Whoami.
Home-page: https://xllmoon.web.app
Author: Chaos and whoami.exe
Author-email: nonono@nono.no
License: UNKNOWN
Platform: UNKNOWN
